serialpacker.py
serialpacker-0.10.3.dist-info/LICENSE
serialpacker-0.10.3.dist-info/METADATA
serialpacker-0.10.3.dist-info/WHEEL
serialpacker-0.10.3.dist-info/top_level.txt
serialpacker-0.10.3.dist-info/RECORD
