Metadata-Version: 2.1
Name: serialpacker
Version: 0.10.3
Summary: REPLACE ME
Author-email: Matthias Urlichs <matthias@urlichs.de>
Project-URL: homepage, https://m-o-a-t.org
Project-URL: repository, https://github.com/M-o-a-T/serialpacker
Keywords: serial packer
Classifier: Development Status :: 4 - Beta
Classifier: License :: OSI Approved
Classifier: Framework :: AnyIO
Classifier: Framework :: Trio
Classifier: Framework :: AsyncIO
Classifier: Programming Language :: Python :: 3
Classifier: Intended Audience :: Developers
Requires-Python: >=3.8
License-File: LICENSE
Requires-Dist: anyio (~=3.0)
